odoo/addons/l10n_br_coa/README.rst
odoo/addons/l10n_br_coa/__init__.py
odoo/addons/l10n_br_coa/__manifest__.py
odoo/addons/l10n_br_coa/data/account_tax_group.xml
odoo/addons/l10n_br_coa/data/account_tax_tag.xml
odoo/addons/l10n_br_coa/data/account_tax_template.xml
odoo/addons/l10n_br_coa/data/account_type_data.xml
odoo/addons/l10n_br_coa/data/l10n_br_coa_template.xml
odoo/addons/l10n_br_coa/i18n/l10n_br_coa.pot
odoo/addons/l10n_br_coa/i18n/pt_BR.po
odoo/addons/l10n_br_coa/models/__init__.py
odoo/addons/l10n_br_coa/models/account_chart_template.py
odoo/addons/l10n_br_coa/models/account_tax.py
odoo/addons/l10n_br_coa/models/account_tax_mixin.py
odoo/addons/l10n_br_coa/models/account_tax_template.py
odoo/addons/l10n_br_coa/models/l10n_br_coa_account_tax_group_account_template.py
odoo/addons/l10n_br_coa/readme/CONFIGURE.rst
odoo/addons/l10n_br_coa/readme/CONTRIBUTORS.rst
odoo/addons/l10n_br_coa/readme/DESCRIPTION.rst
odoo/addons/l10n_br_coa/readme/INSTALL.rst
odoo/addons/l10n_br_coa/readme/ROADMAP.rst
odoo/addons/l10n_br_coa/readme/USAGE.rst
odoo/addons/l10n_br_coa/security/ir.model.access.csv
odoo/addons/l10n_br_coa/static/description/icon.png
odoo/addons/l10n_br_coa/static/description/index.html
odoo/addons/l10n_br_coa/views/account_tax.xml
odoo/addons/l10n_br_coa/views/account_tax_template.xml
odoo12_addon_l10n_br_coa-12.0.4.0.0.dist-info/METADATA
odoo12_addon_l10n_br_coa-12.0.4.0.0.dist-info/WHEEL
odoo12_addon_l10n_br_coa-12.0.4.0.0.dist-info/top_level.txt
odoo12_addon_l10n_br_coa-12.0.4.0.0.dist-info/RECORD
