Metadata-Version: 2.1
Name: odoo12-addon-l10n-br-coa
Version: 12.0.4.0.0
Summary: Base do Planos de Contas brasileiros
Home-page: https://github.com/OCA/l10n-brazil
Author: Akretion, KMEE, Odoo Community Association (OCA)
Author-email: support@odoo-community.org
License: AGPL-3
Platform: UNKNOWN
Classifier: Programming Language :: Python
Classifier: Framework :: Odoo
Classifier: License :: OSI Approved :: GNU Affero General Public License v3
Classifier: Development Status :: 5 - Production/Stable
Requires-Python: >=3.5
Requires-Dist: odoo (<12.1dev,>=12.0a)
